pymdocx/__init__.py
pymdocx/common/__init__.py
pymdocx/common/comment.py
pymdocx/common/constants.py
pymdocx/common/revision.py
pymdocx/common/utils.py
pymdocx/doc/__init__.py
pymdocx/doc/paragraph.py
pymdocx/doc/table.py
pymdocx/oxml/__init__.py
pymdocx/oxml/revision.py
pymdocx/text/__init__.py
pymdocx/text/revision.py
pymdocx-0.4.1.dist-info/LICENSE.txt
pymdocx-0.4.1.dist-info/METADATA
pymdocx-0.4.1.dist-info/WHEEL
pymdocx-0.4.1.dist-info/top_level.txt
pymdocx-0.4.1.dist-info/RECORD
