Metadata-Version: 2.1
Name: pymdocx
Version: 0.4.1
Summary: pydocx is a Python library for merging revised and commented Microsoft Word files.
Home-page: https://github.com/mirrornight/pydocx
Author: mirrornight
Author-email: mirrornighth@gmail.com
License: MIT License
Platform: all
Classifier: Operating System :: OS Independent
Classifier: Programming Language :: Python :: 3
Classifier: Programming Language :: Python :: 3.5
Classifier: Programming Language :: Python :: 3.6
Classifier: Programming Language :: Python :: 3.7
Classifier: Programming Language :: Python :: 3.8
License-File: LICENSE.txt
Requires-Dist: bayoo-docx (==0.2.17)
